{
    "DNDConfig": null,
    "__parentReadjusting__": false,
    "_bottom_": {
        "type": "string",
        "value": "0dp"
    },
    "_height_": {
        "type": "string",
        "value": "50%"
    },
    "_margin_": [
        0,
        0,
        0,
        0
    ],
    "_orientation_": 6,
    "_padding_": [
        0,
        0,
        0,
        0
    ],
    "_percent_": true,
    "_right_": {
        "type": "string",
        "value": "0dp"
    },
    "_skin_": "sf46a0056b534ebc8dc0c7106ca7c9e5",
    "_width_": {
        "type": "string",
        "value": "33.33%"
    },
    "allboxes": [],
    "autogrowmode": 0,
    "canUpdateUI": true,
    "children": [
        "lblMaxExpensesName",
        "lblMaxExpensesValue"
    ],
    "clipbounds": true,
    "containerweight": 100,
    "enablescrolling": true,
    "id": "flxMaxExpenses",
    "info": null,
    "iscustomlayout": false,
    "isvisible": true,
    "kuid": "i63c564788a44a10b88f2db2ee722585",
    "layouttype": 2,
    "name": "kony.ui.FlexContainer",
    "parent": "fxlTableWrapper",
    "pf": "frmExpensesHistory",
    "retaincontentalignment": false,
    "retainflexpositionproperties": false,
    "snapgridsize": 10,
    "snaptogrid": true,
    "wType": "FlexContainer",
    "widgetalignment": 1,
    "zindex": 1
}