{
    "@class": "com.kony.gen.viz.model.component.KVizTextBox2",
    "DNDConfig": null,
    "__parentReadjusting__": false,
    "_height_": {
        "type": "string",
        "value": "40dp"
    },
    "_left_": {
        "type": "string",
        "value": "35%"
    },
    "_margin_": [
        0,
        0,
        0,
        0
    ],
    "_padding_": [
        3,
        0,
        0,
        0
    ],
    "_placeholder_": "Old password",
    "_skin_": "s6980faa463d4c9197b26bd2d1c398a8",
    "_text_": "",
    "_top_": {
        "type": "string",
        "value": "0dp"
    },
    "_width_": {
        "type": "string",
        "value": "60%"
    },
    "autocapitalize": "none",
    "autocomplete": false,
    "autocorrect": false,
    "autofilter": false,
    "canUpdateUI": true,
    "containerheight": "",
    "containerheightmode": 1,
    "containerweight": 100,
    "contentalignment": 4,
    "focusskin": "sab74807df994273ab3b0a9dc946fbbc",
    "id": "txbOldPassword1",
    "info": null,
    "iscustomlayout": false,
    "isvisible": true,
    "keyboardtype": "A",
    "kuid": "c775ae6b95be482183c0f88ea449ea29",
    "mode": "A",
    "name": "kony.ui.TextBox2",
    "parent": "flxOldPasswordContainer1",
    "pf": "frmSettings",
    "placeholderskin": "s214d8f7d7fe4ab29a0ebc542cdc3b41",
    "retaincontentalignment": false,
    "retainflexpositionproperties": false,
    "securetextentry": true,
    "textinputmode": "A",
    "tooltip": "",
    "viewtype": "default",
    "wType": "TextField",
    "zindex": 1
}